[
    {
        "center": {
            "x": 3.8061697996685204,
            "y": 3.487474074753676,
            "z": 0
        },
        "width": 0.789536,
        "height": 0.6459840000000001
    },
    {
        "center": {
            "x": 4.396828829901631,
            "y": -2.5261876638908856,
            "z": 0
        },
        "width": 0.251216,
        "height": 0.7536480000000001
    },
    {
        "center": {
            "x": -0.6135026695686614,
            "y": -3.489330684672367,
            "z": 0
        },
        "width": 0.8613120000000001,
        "height": 0.6459840000000001
    }
]